{
    "name": "Wartortle",
    "infos": [
        "1.0 m",
        "22.5 kg"
    ],
    "abilities": [
        {
            "name": "torrent",
            "url": "https://pokeapi.co/api/v2/ability/67/"
        }
    ],
    "gender": "M/F",
    "types": [
        "Water"
    ],
    "defensive_offensive": {
        "defensive": {
            "double_damage_from": [
                [
                    "Grass",
                    "Electric"
                ]
            ],
            "half_damage_from": [
                [
                    "Steel",
                    "Fire",
                    "Water",
                    "Ice"
                ]
            ]
        },
        "offensive": {
            "double_damage_to": [
                [
                    "Ground",
                    "Rock",
                    "Fire"
                ]
            ],
            "half_damage_to": [
                [
                    "Water",
                    "Grass",
                    "Dragon"
                ]
            ]
        }
    },
    "evolutions": [
        "Squirtle",
        "WARTORTLE",
        "Blastoise"
    ]
}